{
    "title": "PsySutra - Nebulla Cebulla (2016)",
    "description": "\u25ba Subscribe: http:\/\/bit.ly\/SubscribeNeogoa\n\nAfter the release of his debut album 'Gamma Phoenicis' on Cronomi Records, back in summer of 2014, one of the most creative Goa trance producers from Poland - \u0141ukasz Wi\u0105cek returns with his PsySutra project and new 4-track EP 'Nebulla Cebulla' on Neogoa Records.  Download Nebulla Cebulla - http:\/\/www.neogoa.net\/nebulla-cebulla\/\n\nTracklist:\n\n01 \u2013 PsySutra - Infinnitus Anniversarius (146 BPM)\n02 \u2013 PsySutra - Semper Fi (150 BPM)\n03 \u2013 Artha - Insidelamp (PsySutra Remix) (136 BPM)\n04 \u2013 PsySutra - Air Trance Corporation (Red Sun Rising Remix) (114 BPM)\n\nFor more free Goa trance and ambient music, please visit us:\n\nWebsite - http:\/\/www.neogoa.net\nFacebook - https:\/\/www.facebook.com\/neogoarecords\nTwitter - https:\/\/www.twitter.com\/neogoarecords\nInstagram - https:\/\/www.instagram.com\/neogoarecords\nSoundcloud - https:\/\/soundcloud.com\/neogoarecords\nGoogle+ - https:\/\/plus.google.com\/+neogoarecords\nBandcamp - https:\/\/neogoarecords.bandcamp.com\n\nMore PsySutra:\nhttp:\/\/www.neogoa.net\/psysutra",
    "referenceId": "JbwlQsncHoA",
    "date_created": "1480505835",
    "date_modified": "1494456108",
    "tags": "",
    "sourceId": "4",
    "VIDEO_LENGTH": "LONG",
    "status": "approved",
    "visibility": "1",
    "VV_VI": null,
    "CVV_VI": null,
    "engagement_score": null,
    "conversion_score": null,
    "id": "90952406",
    "loginId": "1758397",
    "entityType": "1",
    "titleTextEncoded": "PsySutra-Nebulla-Cebulla-2016",
    "category": "",
    "duration": 2323,
    "settings": "",
    "asset": {
        "type": "youtube",
        "thumbnailUrl": "https:\/\/i.ytimg.com\/vi\/JbwlQsncHoA\/hqdefault.jpg",
        "uploadDate": 1480505835,
        "videoId": "JbwlQsncHoA",
        "title": "PsySutra - Nebulla Cebulla (2016)",
        "description": "\u25ba Subscribe: http:\/\/bit.ly\/SubscribeNeogoa\n\nAfter the release of his debut album 'Gamma Phoenicis' on Cronomi Records, back in summer of 2014, one of the most creative Goa trance producers from Poland - \u0141ukasz Wi\u0105cek returns with his PsySutra project and new 4-track EP 'Nebulla Cebulla' on Neogoa Records.  Download Nebulla Cebulla - http:\/\/www.neogoa.net\/nebulla-cebulla\/\n\nTracklist:\n\n01 \u2013 PsySutra - Infinnitus Anniversarius (146 BPM)\n02 \u2013 PsySutra - Semper Fi (150 BPM)\n03 \u2013 Artha - Insidelamp (PsySutra Remix) (136 BPM)\n04 \u2013 PsySutra - Air Trance Corporation (Red Sun Rising Remix) (114 BPM)\n\nFor more free Goa trance and ambient music, please visit us:\n\nWebsite - http:\/\/www.neogoa.net\nFacebook - https:\/\/www.facebook.com\/neogoarecords\nTwitter - https:\/\/www.twitter.com\/neogoarecords\nInstagram - https:\/\/www.instagram.com\/neogoarecords\nSoundcloud - https:\/\/soundcloud.com\/neogoarecords\nGoogle+ - https:\/\/plus.google.com\/+neogoarecords\nBandcamp - https:\/\/neogoarecords.bandcamp.com\n\nMore PsySutra:\nhttp:\/\/www.neogoa.net\/psysutra",
        "author": "Neogoa Records",
        "mediaDuration": 2323,
        "prettyDuration": "00:38:43",
        "views": "504"
    },
    "transcripts": "",
    "metrics_statistics": null,
    "tvp_profiles": [
        "11"
    ],
    "tvp_profiles_manual": null,
    "tvp_profiles_maxscore": 960.0224
}